{
  "date": "2025-11-21",
  "divisions": {
    "Atlantic": {
      "DET": 1,
      "BOS": 2,
      "TBL": 3,
      "FLA": 4,
      "MTL": 5,
      "OTT": 6,
      "TOR": 7,
      "BUF": 8
    },
    "Metropolitan": {
      "CAR": 1,
      "NJ": 2,
      "NYI": 3,
      "CBJ": 4,
      "WSH": 5,
      "PIT": 6,
      "PHI": 7,
      "NYR": 8
    },
    "Central": {
      "COL": 1,
      "DAL": 2,
      "WPG": 3,
      "CHI": 4,
      "MIN": 5,
      "UTA": 6,
      "STL": 7,
      "NSH": 8
    },
    "Pacific": {
      "ANA": 1,
      "VGK": 2,
      "SEA": 3,
      "LAK": 4,
      "EDM": 5,
      "SJ": 6,
      "VAN": 7,
      "CGY": 8
    }
  }
}